mkid_detect/cosmic_rays.py
mkid_detect/mkid_detect.py
mkid_detect/photon_list.py
mkid_detect/utils.py
mkid_detect-0.1.1.dist-info/METADATA
mkid_detect-0.1.1.dist-info/WHEEL
mkid_detect-0.1.1.dist-info/licenses/LICENSE
mkid_detect-0.1.1.dist-info/RECORD
