Metadata-Version: 2.3
Name: mkid_detect
Version: 0.1.1
Summary: A tool for generating simulated MKID outputs.
Project-URL: Homepage, https://github.com/steigersg/mkid_detect
Project-URL: Issues, https://github.com/steigersg/mkid_detect/issues
Author-email: Sarah Steiger <ssteiger@stsci.edu>
License: MIT License
License-File: LICENSE
Requires-Python: >=3.7
Requires-Dist: hcipy
Requires-Dist: matplotlib
Requires-Dist: numpy
Requires-Dist: tables
